skorkart/__init__.py
skorkart/data_fetcher.py
skorkart/setup_webdriver.py
skorkart/utils.py
skorkart-0.1.0.dist-info/LICENSE
skorkart-0.1.0.dist-info/METADATA
skorkart-0.1.0.dist-info/WHEEL
skorkart-0.1.0.dist-info/top_level.txt
skorkart-0.1.0.dist-info/RECORD
