Metadata-Version: 2.1
Name: skorkart
Version: 0.1.0
Summary: Fetches financial scorecard tables for BIST stocks from Halk Yatırım portal.
Home-page: https://github.com/urazakgul/skorkart
Author: Uraz Akgül
Author-email: urazdev@gmail.com
License: MIT
Classifier: Programming Language :: Python :: 3
Classifier: License :: OSI Approved :: MIT License
Requires-Python: >=3.9
License-File: LICENSE
Requires-Dist: pandas
Requires-Dist: selenium
Requires-Dist: lxml
Requires-Dist: webdriver-manager
Requires-Dist: openpyxl
